verdict_hasher/__init__.py
verdict_hasher/__main__.py
verdict_hasher/file_config.py
verdict_hasher/hash_file.py
verdict_hasher/main.py
verdict_hasher/path_config.py
verdict_hasher_cli-0.1.0.dist-info/METADATA
verdict_hasher_cli-0.1.0.dist-info/WHEEL
verdict_hasher_cli-0.1.0.dist-info/top_level.txt
verdict_hasher_cli-0.1.0.dist-info/RECORD
