Metadata-Version: 2.2
Name: verdict_hasher_cli
Version: 0.1.0
Summary: A project for file configuration and hashing
Author-email: Sigireddy Balasai <SigireddyBalasai@gmail.com>, Ella Hart AKA Cyncrovee <86919717+Cyncrovee@user.noreply.github.com>
Requires-Python: >=3.13
Requires-Dist: questionary>=2.1.0
Requires-Dist: tqdm>=4.67.1
